README.rst
setup.py
syrpc/__init__.py
syrpc/client.py
syrpc/common.py
syrpc/constants.py
syrpc/logger.py
syrpc/rpc_base.py
syrpc/runner.py
syrpc/server.py
syrpc/test.py
syrpc.egg-info/PKG-INFO
syrpc.egg-info/SOURCES.txt
syrpc.egg-info/dependency_links.txt
syrpc.egg-info/entry_points.txt
syrpc.egg-info/pbr.json
syrpc.egg-info/requires.txt
syrpc.egg-info/top_level.txt