Metadata-Version: 1.1
Name: syrpc
Version: 1.0
Summary: Adfinis SyGroup SyRPC Services Library
Home-page: http://adfinis-sygroup.ch
Author: Adfinis SyGroup AG
Author-email: http://adfinis-sygroup.ch/contact
License: GNU Library or Lesser General Public License (LGPL)
Keywords: adfinis-sygroup rpc
Platform: UNKNOWN
Classifier: Development Status :: 4 - Beta
Classifier: Environment :: Console
Classifier: Intended Audience :: Developers
Classifier: Intended Audience :: Information Technology
Classifier: License :: OSI Approved :: GNU Library or Lesser General Public License (LGPL)
Classifier: Natural Language :: English
Classifier: Operating System :: OS Independent
Classifier: Programming Language :: Python :: 2.6
Classifier: Programming Language :: Python :: 2.7
Classifier: Programming Language :: Python :: 3.3
Classifier: Programming Language :: Python :: 3.4
